LICENSE
README.md
setup.py
binama/__init__.py
binama/example.py
binama/utils.py
pilab_binama.egg-info/PKG-INFO
pilab_binama.egg-info/SOURCES.txt
pilab_binama.egg-info/dependency_links.txt
pilab_binama.egg-info/requires.txt
pilab_binama.egg-info/top_level.txt