Metadata-Version: 2.1
Name: pilab-binama
Version: 0.0.8
Home-page: https://github.com/PiLAB-Medical-Imaging/BinaryMasks
Author: PiLAB
Author-email: nicolas.delinte@uclouvain.be
License: GNU General Public License v3.0
Classifier: Natural Language :: English
Classifier: Programming Language :: Python
License-File: LICENSE
